functional_recursion/__init__.py
functional_recursion/functional_recursion.py
functional_recursion-1.0.0.dist-info/LICENSE
functional_recursion-1.0.0.dist-info/METADATA
functional_recursion-1.0.0.dist-info/WHEEL
functional_recursion-1.0.0.dist-info/top_level.txt
functional_recursion-1.0.0.dist-info/RECORD
