Metadata-Version: 2.1
Name: functional-recursion
Version: 1.0.0
Summary: Do tail recursion without overflowing with generators and functions.
Home-page: https://github.com/hunterwilhelm/functional-recursion
Author: Hunter Wilhelm
License: MIT
Platform: UNKNOWN
Requires-Python: >=3.8
License-File: LICENSE
